pasha_bank_api/__init__.py
pasha_bank_api/client.py
pasha_bank_api/constants.py
pasha_bank_api/exceptions.py
tests/__init__.py
tests/test_client.py
pasha_bank_api-0.1.0.dist-info/LICENSE
pasha_bank_api-0.1.0.dist-info/METADATA
pasha_bank_api-0.1.0.dist-info/WHEEL
pasha_bank_api-0.1.0.dist-info/top_level.txt
pasha_bank_api-0.1.0.dist-info/RECORD
