Metadata-Version: 2.1
Name: pasha_bank_api
Version: 0.1.0
Summary: A Python client for interacting with PASHA Bank's API.
Home-page: https://github.com/elyasomer/pasha-bank-api
Author: Your Name
Author-email: elyas.ghausi@gmail.com
Classifier: Programming Language :: Python :: 3.11
Classifier: License :: OSI Approved :: MIT License
Classifier: Operating System :: OS Independent
Requires-Python: >=3.11
License-File: LICENSE
Requires-Dist: requests >=2.32.2
